packit/__init__.py
packit/actions.py
packit/actions_handler.py
packit/api.py
packit/base_git.py
packit/command_handler.py
packit/constants.py
packit/copr_helper.py
packit/dist_git_instance.py
packit/distgit.py
packit/exceptions.py
packit/local_project.py
packit/patches.py
packit/pkgtool.py
packit/schema.py
packit/security.py
packit/source_git.py
packit/status.py
packit/sync.py
packit/upstream.py
packit/vm_image_build.py
packit/cli/__init__.py
packit/cli/build.py
packit/cli/config.py
packit/cli/create_update.py
packit/cli/dist_git.py
packit/cli/dist_git_init.py
packit/cli/init.py
packit/cli/options.py
packit/cli/packit_base.py
packit/cli/prepare_sources.py
packit/cli/propose_downstream.py
packit/cli/push_updates.py
packit/cli/scan_in_osh.py
packit/cli/source_git.py
packit/cli/source_git_init.py
packit/cli/source_git_status.py
packit/cli/srpm.py
packit/cli/status.py
packit/cli/sync_from_downstream.py
packit/cli/test.py
packit/cli/types.py
packit/cli/update_dist_git.py
packit/cli/update_source_git.py
packit/cli/utils.py
packit/cli/validate_config.py
packit/cli/builds/__init__.py
packit/cli/builds/copr_build.py
packit/cli/builds/in_image_builder.py
packit/cli/builds/koji_build.py
packit/cli/builds/local_build.py
packit/cli/builds/mock_build.py
packit/cli/builds/obs_build.py
packit/config/__init__.py
packit/config/aliases.py
packit/config/commands.py
packit/config/common_package_config.py
packit/config/config.py
packit/config/job_config.py
packit/config/notifications.py
packit/config/package_config.py
packit/config/package_config_validator.py
packit/config/requirements.py
packit/config/sources.py
packit/data/__init__.py
packit/data/_packitpatch
packit/utils/__init__.py
packit/utils/bodhi.py
packit/utils/changelog_helper.py
packit/utils/commands.py
packit/utils/decorators.py
packit/utils/extensions.py
packit/utils/koji_helper.py
packit/utils/local_test_utils.py
packit/utils/logging.py
packit/utils/lookaside.py
packit/utils/monitoring.py
packit/utils/obs_helper.py
packitos-1.14.0.dist-info/METADATA
packitos-1.14.0.dist-info/WHEEL
packitos-1.14.0.dist-info/entry_points.txt
packitos-1.14.0.dist-info/licenses/LICENSE
packitos-1.14.0.dist-info/RECORD
