Metadata-Version: 2.4
Name: packitos
Version: 1.14.0
Summary: A set of tools to integrate upstream open source projects into Fedora operating system.
Project-URL: Homepage, https://github.com/packit/packit
Author-email: Red Hat <packit@redhat.com>
License-Expression: MIT
License-File: LICENSE
Keywords: dist-git,fedora,git,packaging,rpm
Classifier: Development Status :: 4 - Beta
Classifier: Environment :: Console
Classifier: Intended Audience :: Developers
Classifier: Operating System :: POSIX :: Linux
Classifier: Programming Language :: Python
Classifier: Programming Language :: Python :: 3
Classifier: Programming Language :: Python :: 3 :: Only
Classifier: Programming Language :: Python :: 3.9
Classifier: Programming Language :: Python :: 3.10
Classifier: Programming Language :: Python :: 3.11
Classifier: Topic :: Software Development
Classifier: Topic :: Utilities
Requires-Python: >=3.9
Requires-Dist: backoff
Requires-Dist: bodhi-client>=7.0.0
Requires-Dist: cachetools
Requires-Dist: cccolutils
Requires-Dist: click
Requires-Dist: copr
Requires-Dist: fedora-distro-aliases
Requires-Dist: gitpython
Requires-Dist: koji
Requires-Dist: lazy-object-proxy
Requires-Dist: marshmallow>=3.18.0
Requires-Dist: munch
Requires-Dist: ogr
Requires-Dist: opensuse-distro-aliases
Requires-Dist: osc!=1.8.2,>=1.6.2
Requires-Dist: packaging
Requires-Dist: python-bugzilla
Requires-Dist: python-gnupg
Requires-Dist: pyyaml
Requires-Dist: requests
Requires-Dist: requests-kerberos
Requires-Dist: rpkg
Requires-Dist: specfile
Requires-Dist: tabulate
Provides-Extra: dev
Requires-Dist: deepdiff; extra == 'dev'
Requires-Dist: distro; extra == 'dev'
Requires-Dist: flexmock; extra == 'dev'
Requires-Dist: pre-commit; extra == 'dev'
Requires-Dist: pytest; extra == 'dev'
Requires-Dist: pytest-cov; extra == 'dev'
Requires-Dist: pytest-timeout; extra == 'dev'
Requires-Dist: setuptools; extra == 'dev'
Requires-Dist: setuptools-scm; extra == 'dev'
Provides-Extra: testing
Requires-Dist: deepdiff; extra == 'testing'
Requires-Dist: distro; extra == 'testing'
Requires-Dist: flexmock; extra == 'testing'
Requires-Dist: pytest; extra == 'testing'
Requires-Dist: pytest-cov; extra == 'testing'
Requires-Dist: pytest-timeout; extra == 'testing'
Requires-Dist: setuptools; extra == 'testing'
Requires-Dist: setuptools-scm; extra == 'testing'
